{
    "movies": {
        {
            "id": 1,
            "title": "Avengers 4",
            "image": "assets/avengers-4.jpg",
            "isWatched": true,
            "isFav": true
        },
        {
            "id": 2,
            "title": "Avatar 2",
            "image":"assets/avatar-2.jpg",
            "isWatched": false,
            "isFav": false
        },
        {
            "id": 3,
            "title": "Black widow",
            "image": "assets/black-widow.jpg",
            "isWatched": false,
            "isFav": false
        },
        {
            "id": 4,
            "title": "Matrix",
            "image": "assets/matrix.jpg",
            "isWatched": false,
            "isFav": false
        },
        {
            "id": 5,
            "title": "Army of Thieves",
            "image": "assets/army-of-thieves-jpg",
            "isWatched": false,
            "isFav": false
        },
        {
            "id":  6,
            "title": "Finch",
            "image": "assets/finch.jpg",
            "isWatched": true,
            "isFav": false
        },
        {
            "id": 7,
            "title": "Light Years",
            "image": "assets/light-years.jpg",
            "isWatched": false,
            "isFav": false 
        },
        {
            "id": 8,
            "title": "No Time To Die",
            "image": "assets/no-time-to-die.jpg",
            "isWatched": true,
            "isFav": false
        },
        {
            "id": 9,
            "title": "Super Mario",
            "image": "assets/super-mario.jpg",
            "isWatched": false,
            "isFav": false
        },
        {
            "id": 10,
            "title": "Venom",
            "image": "assets/venom.jpg",
            "isWatched": true,
            "isFav": false
        }
    }
}